README.md
setup.py
pytest_tomato/__init__.py
pytest_tomato/plugin.py
pytest_tomato.egg-info/PKG-INFO
pytest_tomato.egg-info/SOURCES.txt
pytest_tomato.egg-info/dependency_links.txt
pytest_tomato.egg-info/entry_points.txt
pytest_tomato.egg-info/not-zip-safe
pytest_tomato.egg-info/requires.txt
pytest_tomato.egg-info/top_level.txt